LICENSE.txt
README.md
setup.cfg
setup.py
Topyfic/__init__.py
Topyfic/analysis.py
Topyfic/main.py
Topyfic/topModel.py
Topyfic/topic.py
Topyfic/train.py
Topyfic/utilsAnalyseModel.py
Topyfic/utilsMakeModel.py
Topyfic.egg-info/PKG-INFO
Topyfic.egg-info/SOURCES.txt
Topyfic.egg-info/dependency_links.txt
Topyfic.egg-info/requires.txt
Topyfic.egg-info/top_level.txt